plexurl
