Metadata-Version: 1.1
Name: plexurl
Version: 1.3.1
Summary: Browse Plex from CLI. Returns transcoding streaming urls to stdout
Home-page: https://blha303.github.io/plexurl/
Author: Steven Smith
Author-email: stevensmith.ome@gmail.com
License: MIT
Platform: UNKNOWN
Classifier: Development Status :: 4 - Beta
Classifier: License :: OSI Approved :: MIT License
Classifier: Programming Language :: Python :: 2.7
Classifier: Programming Language :: Python :: 2
Classifier: Programming Language :: Python :: 3.4
Classifier: Programming Language :: Python :: 3
Classifier: Intended Audience :: End Users/Desktop
Classifier: Intended Audience :: System Administrators
Classifier: Topic :: Multimedia :: Sound/Audio
